{
    "homepage": "https://github.com/cloudposse/atmos/",
    "description": "atmos: Universal Tool for DevOps and Cloud Automation.",
    "license": "Apache-2.0",
    "version": "1.216.0",
    "architecture": {
        "64bit": {
            "bin": "atmos.exe",
            "hash": "01f55a1522044ad6a50ac6038c9889c4f2ae49db847d2df3a54ffe84485fe43e",
            "url": "https://github.com/cloudposse/atmos/releases/download/v1.216.0/atmos_1.216.0_windows_amd64.exe#/atmos.exe"
        },
        "arm64": {
            "bin": "atmos.exe",
            "hash": "21223c4958553f4126f5053b2b160e3c7f5d958302fa0d5bce040c71a6f08547",
            "url": "https://github.com/cloudposse/atmos/releases/download/v1.216.0/atmos_1.216.0_windows_arm64.exe#/atmos.exe"
        }
    },
    "checkver": {
        "github": "https://github.com/cloudposse/atmos/"
    },
    "autoupdate": {
        "architecture": {
            "64bit": {
                "url": "https://github.com/cloudposse/atmos/releases/download/v$version/atmos_$version_windows_amd64.exe#/atmos.exe"
            },
            "arm64": {
                "url": "https://github.com/cloudposse/atmos/releases/download/v$version/atmos_$version_windows_arm64.exe#/atmos.exe"
            }
        }
    }
}
