{
    "homepage": "https://github.com/iann0036/iamlive/",
    "description": "iamlive: Generate an IAM policy from AWS calls using client-side monitoring (CSM) or embedded proxy",
    "license": "MIT",
    "version": "1.1.4",
    "architecture": {
        "64bit": {
            "bin": "iamlive.exe",
            "hash": "290806173a139ecdd500a29e27ea00d1a236e96c2e2a39f8e9e03ba00d057533",
            "url": "https://github.com/iann0036/iamlive/releases/download/v1.1.4/iamlive-v1.1.4-windows-amd64.zip"
        }
    },
    "checkver": {
        "github": "https://github.com/iann0036/iamlive/"
    },
    "autoupdate": {
        "architecture": {
            "64bit": {
                "url": "https://github.com/iann0036/iamlive/releases/download/v$version/iamlive-v$version-windows-amd64.zip"
            }
        }
    }
}
